nbtestlib/__init__.py
nbtestlib-0.0.1.dist-info/METADATA
nbtestlib-0.0.1.dist-info/WHEEL
nbtestlib-0.0.1.dist-info/top_level.txt
nbtestlib-0.0.1.dist-info/RECORD
