Metadata-Version: 2.4
Name: nbtestlib
Version: 0.0.1
Summary: A testlib package for test
Author: fishbar
Classifier: Programming Language :: Python :: 3
Classifier: License :: OSI Approved :: MIT License
Classifier: Operating System :: OS Independent
Requires-Python: >=3.9
Dynamic: author
Dynamic: classifier
Dynamic: requires-python
Dynamic: summary
